pepedd/__init__.py
pepedd/core/__init__.py
pepedd/core/node_register.py
pepedd/core/objects/__init__.py
pepedd/core/objects/lq_hq_state.py
pepedd/core/objects/node_base.py
pepedd/core/objects/safe_rng.py
pepedd/core/pipeline/__init__.py
pepedd/core/pipeline/pipeline.py
pepedd/core/pipeline/process.py
pepedd/core/pipeline/schema.py
pepedd/core/pipeline/utils.py
pepedd-0.1.2.dist-info/METADATA
pepedd-0.1.2.dist-info/WHEEL
pepedd-0.1.2.dist-info/top_level.txt
pepedd-0.1.2.dist-info/RECORD
